"Outlier_3292/3292_outlier,py.py"
Outlier_3292/3292_outliers.py
Outlier_3292/iris_out.py
OUTLIER_101703292-1.0.1.dist-info/LICENSE.txt
OUTLIER_101703292-1.0.1.dist-info/METADATA
OUTLIER_101703292-1.0.1.dist-info/WHEEL
OUTLIER_101703292-1.0.1.dist-info/entry_points.txt
OUTLIER_101703292-1.0.1.dist-info/top_level.txt
OUTLIER_101703292-1.0.1.dist-info/RECORD
