Metadata-Version: 2.1
Name: OUTLIER-101703292
Version: 1.0.1
Summary: A Python package to remove outliers from a dataset
Home-page: UNKNOWN
Author: Kriti Pandey
Author-email: kritip105@gmail.com
License: MIT
Platform: UNKNOWN
Classifier: License :: OSI Approved :: MIT License
Classifier: Programming Language :: Python :: 3
Classifier: Programming Language :: Python :: 3.7
Requires-Dist: numpy
Requires-Dist: pandas
